sujal/design/digital_design.v
module digital_design (
    input wire clk,
    input wire reset,
    input wire x,
    output reg z
);

    parameter A = 2'b00,
              B = 2'b01,
              C = 2'b10;

    reg [1:0] current_state, next_state;

    always @(*) begin
        case (current_state)
            A: next_state = x ? B : A;
            B: next_state = x ? C : B;
            C: next_state = x ? C : A;
            default: next_state = A;
        endcase
    end

    always @(*) begin
        z = (current_state == C) & x;
    end

    always @(posedge clk or posedge reset) begin
        if (reset)
            current_state <= A;
        else
            current_state <= next_state;
    end

endmodule

sujal/design/digital_tb.v
`timescale 1ns / 1ps

module digital_tb;

    reg clk;
    reg reset;
    reg x;

    wire z;

    wire [8*5:1] state_string;

    digital_design uut (
        .clk(clk), 
        .reset(reset), 
        .x(x), 
        .z(z)
    );

    initial begin
        clk = 0;
        forever #5 clk = ~clk;  // 100MHz clock
    end

    initial begin
        $dumpfile("digital_design.vcd");
        $dumpvars(0, digital_tb);
    end

    function [8*5:1] state_to_string;
        input [1:0] state;
        begin
            case(state)
                2'b00: state_to_string = "A    ";
                2'b01: state_to_string = "B    ";
                2'b10: state_to_string = "C    ";
                default: state_to_string = "UNKN ";
            endcase
        end
    endfunction

    assign state_string = state_to_string(uut.current_state);

    initial begin
        reset = 1;
        x = 0;

        #100;
        reset = 0;

        #10 x = 0;
        
        #10 x = 1;
        
        #10 x = 1;
        
        #10 x = 1;
        
        #10 x = 0;
        
        #10 x = 1;
        #10 x = 1;
        
        #10 x = 0;
        #10 x = 0;

        #100 $finish;
    end

    initial begin
        $monitor("Time=%0t, Reset=%b, X=%b, Z=%b, State=%s", 
                 $time, reset, x, z, state_string);
    end

endmodule

sujal/design/digital_design.vcd
$date
	Mon Jul 15 22:39:32 2024
$end
$version
	Icarus Verilog
$end
$timescale
	1ps
$end
$scope module digital_tb $end
$var wire 1 ! z $end
$var wire 40 " state_string [40:1] $end
$var reg 1 # clk $end
$var reg 1 $ reset $end
$var reg 1 % x $end
$scope function state_to_string $end
$var reg 2 & state [1:0] $end
$upscope $end
$scope module uut $end
$var wire 1 # clk $end
$var wire 1 $ reset $end
$var wire 1 % x $end
$var reg 2 ' current_state [1:0] $end
$var reg 2 ( next_state [1:0] $end
$var reg 1 ! z $end
$upscope $end
$upscope $end
$enddefinitions $end
#0
$dumpvars
b0 (
b0 '
b0 &
0%
1$
0#
b100000100100000001000000010000000100000 "
0!
$end
#5000
1#
#10000
0#
#15000
1#
#20000
0#
#25000
1#
#30000
0#
#35000
1#
#40000
0#
#45000
1#
#50000
0#
#55000
1#
#60000
0#
#65000
1#
#70000
0#
#75000
1#
#80000
0#
#85000
1#
#90000
0#
#95000
1#
#100000
0#
0$
#105000
1#
#110000
0#
#115000
1#
#120000
b1 (
0#
1%
#125000
b10 (
b100001000100000001000000010000000100000 "
b1 &
b1 '
1#
#130000
0#
#135000
1!
b100001100100000001000000010000000100000 "
b10 &
b10 '
1#
#140000
0#
#145000
1#
#150000
b0 (
0!
0#
0%
#155000
b100000100100000001000000010000000100000 "
b0 &
b0 '
1#
#160000
b1 (
0#
1%
#165000
b10 (
b100001000100000001000000010000000100000 "
b1 &
b1 '
1#
#170000
0#
#175000
1!
b100001100100000001000000010000000100000 "
b10 &
b10 '
1#
#180000
0!
b0 (
0#
0%
#185000
b100000100100000001000000010000000100000 "
b0 &
b0 '
1#
