bhavesh/verilog/convolution/convolution.v
module convolution(
input clk,
input rst,
input enable,
input values,
input convolve,
input [647:0] IMG,
output reg [8:0]MASK,
output reg [647:0] ConvIMG,
output reg done
);

reg signed [8:0] matIMG[8:0][8:0];
reg signed [8:0] matMASK[2:0][2:0];
//reg signed [8:0] matConvIMG[8:0][8:0];
integer i, j;
integer m, n;
reg [15:0] temp;
integer x;
//reg values;
//reg convolve;

//kernel for GAUSSIAN-BLUR
initial begin
matMASK[0][0] = 2; matMASK[0][1] = 1; matMASK[0][2] = 2;
matMASK[1][0] = 1; matMASK[1][1] = 6; matMASK[1][2] = 1;
matMASK[2][0] = 2; matMASK[2][1] = 1; matMASK[2][2] = 2;
end

initial begin
$display("gaussian blur kernel: ");
for(i=0; i<=2; i=i+1)begin
   for(j=0; j<=2; j=j+1)begin
      $write(matMASK[i][j]);
   end
   $write ("\n");
end
end


always@(posedge clk or posedge rst or posedge enable)begin
    if(rst==1)begin
       //$display("reset flag ON start");
       for(i=0; i<=8; i=i+1)begin
           for(j=0; j<=8; j=j+1)begin
               matIMG[i][j] <= 8'd0;
               //matConvIMG[i][j] <= 8'd0;
               //$write(matIMG[i][j]);
           end
           //$write("\n");
       end
       i = 0;
       j = 0;
       m = 0;
       n = 0;
      
       //values = 0;
       //convolve = 0;
       temp = 8'd0;
      //$display("reset flag ON end"); 
    end  
    else begin
       if(enable==1)begin
          //values = 1;
          //$display("enable is ON start");
          if(values==1)begin
          
             for(i=0;i<=8;i=i+1)begin
                 for(j=0;j<=8;j=j+1)begin
                 matIMG[i][j] = IMG[(i*9 + j)*8 +: 8];
                 //matConvIMG[i][j] = 8'd0;
                 end
             end
             i = 0;
             j = 0;
             m = 0;
             n = 0;
             x = 0;
             //values=0;
             //convolve=1;
           //$display("values ON");  
          end
          else if(convolve==1)begin
          //$display("convolve on ");
                 temp = temp + (matMASK[i][j])*(matIMG[i+m][j+n]);
                 ConvIMG[8*x +: 8] = temp;
                 if(j==2)begin 
                   j<=0;
                   if(i==2)begin
                     i<=0;
                     
                     x = x + 1;
                     if(n==6)begin
                       n<=0;
                       if(m==6)begin
                         m<=0;
                         done = 1;
                       end
                       else
                       
                         m=m+1;
                     end
                     else
                     
                     n=n+1;
                   end
                   else
                   
                   i=i+1;
                 end
                 else 
                 
                 j=j+1;
          end
          //else if(convolve==0)begin
          //$display("convolve off");
          //       done = 1;
          //end
       end
    end
end

endmodule

bhavesh/verilog/convolution/convolution_tb.v
module convolution_tb;
reg clk;
reg rst;
reg enable;
reg convolve;
reg values;
reg [647:0] IMG;
wire [8:0] MASK;
wire [647:0] ConvIMG;
wire done;


convolution uut(
.clk(clk),
.rst(rst),
.enable(enable),
.IMG(IMG),
.MASK(MASK),
.ConvIMG(ConvIMG),
.done(done),
.convolve(convolve),
.values(values)
);

integer i, j;


initial begin
$dumpfile("convolution.vcd");
$dumpvars(0, convolution_tb);
end


initial begin
clk=0;
forever #5 clk = ~clk;
end



initial begin
rst = 1;

#100;
rst = 0;
enable = 1;
values=0;

#100;
//enable = 1;
values = 1;
for(i=0; i<=8; i=i+1)begin
   for(j=0; j<=8; j=j+1)begin
      IMG[(i*9 + j)*8 +: 8] = 3*i + j + 3'd3;
   end
end


#100;
values = 0;
enable = 1; 
convolve = 1;

//displaying input matrix
$display("input matrix: \n");
 for(i=0; i<=8; i=i+1)begin
           for(j=0; j<=8; j=j+1)begin
              $write(" %d", IMG[(i*9 + j)*8 +: 8]);
           end
           $write("\n");
 end


#10000;
convolve = 0;
enable = 0;
values = 0;


//displaying output matrix
$display("output matrix: \n");
 for(i=0; i<=8; i=i+1)begin
    for(j=0; j<=8; j=j+1)begin
       $write(" %d", ConvIMG[(i*9 + j)*8 +: 8]);
    end
       $write("\n");
 end

$finish;

end

endmodule

bhavesh/verilog/convolution/convolution.vcd
$date
	Mon Aug  5 00:09:51 2024
$end
$version
	Icarus Verilog
$end
$timescale
	1s
$end
$scope module convolution_tb $end
$var wire 1 ! done $end
$var wire 9 " MASK [8:0] $end
$var wire 648 # ConvIMG [647:0] $end
$var reg 648 $ IMG [647:0] $end
$var reg 1 % clk $end
$var reg 1 & convolve $end
$var reg 1 ' enable $end
$var reg 1 ( rst $end
$var reg 1 ) values $end
$var integer 32 * i [31:0] $end
$var integer 32 + j [31:0] $end
$scope module uut $end
$var wire 648 , IMG [647:0] $end
$var wire 1 % clk $end
$var wire 1 & convolve $end
$var wire 1 ' enable $end
$var wire 1 ( rst $end
$var wire 1 ) values $end
$var reg 648 - ConvIMG [647:0] $end
$var reg 9 . MASK [8:0] $end
$var reg 1 ! done $end
$var reg 16 / temp [15:0] $end
$var integer 32 0 i [31:0] $end
$var integer 32 1 j [31:0] $end
$var integer 32 2 m [31:0] $end
$var integer 32 3 n [31:0] $end
$var integer 32 4 x [31:0] $end
$upscope $end
$upscope $end
$enddefinitions $end
$comment Show the parameter values. $end
$dumpall
$end
#0
$dumpvars
bx 4
b0 3
b0 2
b0 1
b0 0
b0 /
bx .
bx -
bx ,
bx +
bx *
x)
1(
x'
x&
0%
bx $
bx #
bx "
x!
$end
#5
b0 0
b0 1
1%
#10
0%
#15
b0 0
b0 1
1%
#20
0%
#25
b0 0
b0 1
1%
#30
0%
#35
b0 0
b0 1
1%
#40
0%
#45
b0 0
b0 1
1%
#50
0%
#55
b0 0
b0 1
1%
#60
0%
#65
b0 0
b0 1
1%
#70
0%
#75
b0 0
b0 1
1%
#80
0%
#85
b0 0
b0 1
1%
#90
0%
#95
b0 0
b0 1
1%
#100
0%
0)
1'
0(
#105
1%
#110
0%
#115
1%
#120
0%
#125
1%
#130
0%
#135
1%
#140
0%
#145
1%
#150
0%
#155
1%
#160
0%
#165
1%
#170
0%
#175
1%
#180
0%
#185
1%
#190
0%
#195
1%
#200
0%
b1000110010001000100001001000000001111100011110000111010001110000011011001000000001111100011110000111010001110000011011000110100001100100011000000111010001110000011011000110100001100100011000000101110001011000010101000110100001100100011000000101110001011000010101000101000001001100010010000101110001011000010101000101000001001100010010000100010001000000001111000101000001001100010010000100010001000000001111000011100000110100001100000100010001000000001111000011100000110100001100000010110000101000001001000011100000110100001100000010110000101000001001000010000000011100000110000010110000101000001001000010000000011100000110000001010000010000000011 $
b1000110010001000100001001000000001111100011110000111010001110000011011001000000001111100011110000111010001110000011011000110100001100100011000000111010001110000011011000110100001100100011000000101110001011000010101000110100001100100011000000101110001011000010101000101000001001100010010000101110001011000010101000101000001001100010010000100010001000000001111000101000001001100010010000100010001000000001111000011100000110100001100000100010001000000001111000011100000110100001100000010110000101000001001000011100000110100001100000010110000101000001001000010000000011100000110000010110000101000001001000010000000011100000110000001010000010000000011 ,
b1001 +
b1001 *
1)
#205
b0 4
b0 0
b0 1
1%
#210
0%
#215
b0 0
b0 1
1%
#220
0%
#225
b0 0
b0 1
1%
#230
0%
#235
b0 0
b0 1
1%
#240
0%
#245
b0 0
b0 1
1%
#250
0%
#255
b0 0
b0 1
1%
#260
0%
#265
b0 0
b0 1
1%
#270
0%
#275
b0 0
b0 1
1%
#280
0%
#285
b0 0
b0 1
1%
#290
0%
#295
b0 0
b0 1
1%
#300
0%
b1001 +
b1001 *
1&
0)
#305
b1 1
bx00000110 #
bx00000110 -
b110 /
1%
#310
0%
#315
b10 1
bx00001010 #
bx00001010 -
b1010 /
1%
#320
0%
#325
b0 1
b1 0
bx00010100 #
bx00010100 -
b10100 /
1%
#330
0%
#335
b1 1
bx00011010 #
bx00011010 -
b11010 /
1%
#340
0%
#345
b10 1
bx01000100 #
bx01000100 -
b1000100 /
1%
#350
0%
#355
b0 1
b10 0
bx01001100 #
bx01001100 -
b1001100 /
1%
#360
0%
#365
b1 1
bx01011110 #
bx01011110 -
b1011110 /
1%
#370
0%
#375
b10 1
bx01101000 #
bx01101000 -
b1101000 /
1%
#380
0%
#385
b0 0
b0 1
b1 3
b1 4
bx01111110 #
bx01111110 -
b1111110 /
1%
#390
0%
#395
b1 1
bx1000011001111110 #
bx1000011001111110 -
b10000110 /
1%
#400
0%
#405
b10 1
bx1000101101111110 #
bx1000101101111110 -
b10001011 /
1%
#410
0%
#415
b0 1
b1 0
bx1001011101111110 #
bx1001011101111110 -
b10010111 /
1%
#420
0%
#425
b1 1
bx1001111001111110 #
bx1001111001111110 -
b10011110 /
1%
#430
0%
#435
b10 1
bx1100111001111110 #
bx1100111001111110 -
b11001110 /
1%
#440
0%
#445
b0 1
b10 0
bx1101011101111110 #
bx1101011101111110 -
b11010111 /
1%
#450
0%
#455
b1 1
bx1110101101111110 #
bx1110101101111110 -
b11101011 /
1%
#460
0%
#465
b10 1
bx1111011001111110 #
bx1111011001111110 -
b11110110 /
1%
#470
0%
#475
b0 0
b0 1
b10 3
b10 4
bx0000111001111110 #
bx0000111001111110 -
b100001110 /
1%
#480
0%
#485
b1 1
bx000110000000111001111110 #
bx000110000000111001111110 -
b100011000 /
1%
#490
0%
#495
b10 1
bx000111100000111001111110 #
bx000111100000111001111110 -
b100011110 /
1%
#500
0%
#505
b0 1
b1 0
bx001011000000111001111110 #
bx001011000000111001111110 -
b100101100 /
1%
#510
0%
#515
b1 1
bx001101000000111001111110 #
bx001101000000111001111110 -
b100110100 /
1%
#520
0%
#525
b10 1
bx011010100000111001111110 #
bx011010100000111001111110 -
b101101010 /
1%
#530
0%
#535
b0 1
b10 0
bx011101000000111001111110 #
bx011101000000111001111110 -
b101110100 /
1%
#540
0%
#545
b1 1
bx100010100000111001111110 #
bx100010100000111001111110 -
b110001010 /
1%
#550
0%
#555
b10 1
bx100101100000111001111110 #
bx100101100000111001111110 -
b110010110 /
1%
#560
0%
#565
b0 0
b0 1
b11 3
b11 4
bx101100000000111001111110 #
bx101100000000111001111110 -
b110110000 /
1%
#570
0%
#575
b1 1
bx10111100101100000000111001111110 #
bx10111100101100000000111001111110 -
b110111100 /
1%
#580
0%
#585
b10 1
bx11000011101100000000111001111110 #
bx11000011101100000000111001111110 -
b111000011 /
1%
#590
0%
#595
b0 1
b1 0
bx11010011101100000000111001111110 #
bx11010011101100000000111001111110 -
b111010011 /
1%
#600
0%
#605
b1 1
bx11011100101100000000111001111110 #
bx11011100101100000000111001111110 -
b111011100 /
1%
#610
0%
#615
b10 1
bx00011000101100000000111001111110 #
bx00011000101100000000111001111110 -
b1000011000 /
1%
#620
0%
#625
b0 1
b10 0
bx00100011101100000000111001111110 #
bx00100011101100000000111001111110 -
b1000100011 /
1%
#630
0%
#635
b1 1
bx00111011101100000000111001111110 #
bx00111011101100000000111001111110 -
b1000111011 /
1%
#640
0%
#645
b10 1
bx01001000101100000000111001111110 #
bx01001000101100000000111001111110 -
b1001001000 /
1%
#650
0%
#655
b0 0
b0 1
b100 3
b100 4
bx01100100101100000000111001111110 #
bx01100100101100000000111001111110 -
b1001100100 /
1%
#660
0%
#665
b1 1
bx0111001001100100101100000000111001111110 #
bx0111001001100100101100000000111001111110 -
b1001110010 /
1%
#670
0%
#675
b10 1
bx0111101001100100101100000000111001111110 #
bx0111101001100100101100000000111001111110 -
b1001111010 /
1%
#680
0%
#685
b0 1
b1 0
bx1000110001100100101100000000111001111110 #
bx1000110001100100101100000000111001111110 -
b1010001100 /
1%
#690
0%
#695
b1 1
bx1001011001100100101100000000111001111110 #
bx1001011001100100101100000000111001111110 -
b1010010110 /
1%
#700
0%
#705
b10 1
bx1101100001100100101100000000111001111110 #
bx1101100001100100101100000000111001111110 -
b1011011000 /
1%
#710
0%
#715
b0 1
b10 0
bx1110010001100100101100000000111001111110 #
bx1110010001100100101100000000111001111110 -
b1011100100 /
1%
#720
0%
#725
b1 1
bx1111111001100100101100000000111001111110 #
bx1111111001100100101100000000111001111110 -
b1011111110 /
1%
#730
0%
#735
b10 1
bx0000110001100100101100000000111001111110 #
bx0000110001100100101100000000111001111110 -
b1100001100 /
1%
#740
0%
#745
b0 0
b0 1
b101 3
b101 4
bx0010101001100100101100000000111001111110 #
bx0010101001100100101100000000111001111110 -
b1100101010 /
1%
#750
0%
#755
b1 1
bx001110100010101001100100101100000000111001111110 #
bx001110100010101001100100101100000000111001111110 -
b1100111010 /
1%
#760
0%
#765
b10 1
bx010000110010101001100100101100000000111001111110 #
bx010000110010101001100100101100000000111001111110 -
b1101000011 /
1%
#770
0%
#775
b0 1
b1 0
bx010101110010101001100100101100000000111001111110 #
bx010101110010101001100100101100000000111001111110 -
b1101010111 /
1%
#780
0%
#785
b1 1
bx011000100010101001100100101100000000111001111110 #
bx011000100010101001100100101100000000111001111110 -
b1101100010 /
1%
#790
0%
#795
b10 1
bx101010100010101001100100101100000000111001111110 #
bx101010100010101001100100101100000000111001111110 -
b1110101010 /
1%
#800
0%
#805
b0 1
b10 0
bx101101110010101001100100101100000000111001111110 #
bx101101110010101001100100101100000000111001111110 -
b1110110111 /
1%
#810
0%
#815
b1 1
bx110100110010101001100100101100000000111001111110 #
bx110100110010101001100100101100000000111001111110 -
b1111010011 /
1%
#820
0%
#825
b10 1
bx111000100010101001100100101100000000111001111110 #
bx111000100010101001100100101100000000111001111110 -
b1111100010 /
1%
#830
0%
#835
b0 0
b0 1
b110 3
b110 4
bx000000100010101001100100101100000000111001111110 #
bx000000100010101001100100101100000000111001111110 -
b10000000010 /
1%
#840
0%
#845
b1 1
bx00010100000000100010101001100100101100000000111001111110 #
bx00010100000000100010101001100100101100000000111001111110 -
b10000010100 /
1%
#850
0%
#855
b10 1
bx00011110000000100010101001100100101100000000111001111110 #
bx00011110000000100010101001100100101100000000111001111110 -
b10000011110 /
1%
#860
0%
#865
b0 1
b1 0
bx00110100000000100010101001100100101100000000111001111110 #
bx00110100000000100010101001100100101100000000111001111110 -
b10000110100 /
1%
#870
0%
#875
b1 1
bx01000000000000100010101001100100101100000000111001111110 #
bx01000000000000100010101001100100101100000000111001111110 -
b10001000000 /
1%
#880
0%
#885
b10 1
bx10001110000000100010101001100100101100000000111001111110 #
bx10001110000000100010101001100100101100000000111001111110 -
b10010001110 /
1%
#890
0%
#895
b0 1
b10 0
bx10011100000000100010101001100100101100000000111001111110 #
bx10011100000000100010101001100100101100000000111001111110 -
b10010011100 /
1%
#900
0%
#905
b1 1
bx10111010000000100010101001100100101100000000111001111110 #
bx10111010000000100010101001100100101100000000111001111110 -
b10010111010 /
1%
#910
0%
#915
b10 1
bx11001010000000100010101001100100101100000000111001111110 #
bx11001010000000100010101001100100101100000000111001111110 -
b10011001010 /
1%
#920
0%
#925
b0 3
b0 0
b0 1
b1 2
b111 4
bx11101100000000100010101001100100101100000000111001111110 #
bx11101100000000100010101001100100101100000000111001111110 -
b10011101100 /
1%
#930
0%
#935
b1 1
bx1111100011101100000000100010101001100100101100000000111001111110 #
bx1111100011101100000000100010101001100100101100000000111001111110 -
b10011111000 /
1%
#940
0%
#945
b10 1
bx1111111111101100000000100010101001100100101100000000111001111110 #
bx1111111111101100000000100010101001100100101100000000111001111110 -
b10011111111 /
1%
#950
0%
#955
b0 1
b1 0
bx0000111111101100000000100010101001100100101100000000111001111110 #
bx0000111111101100000000100010101001100100101100000000111001111110 -
b10100001111 /
1%
#960
0%
#965
b1 1
bx0001100011101100000000100010101001100100101100000000111001111110 #
bx0001100011101100000000100010101001100100101100000000111001111110 -
b10100011000 /
1%
#970
0%
#975
b10 1
bx0101010011101100000000100010101001100100101100000000111001111110 #
bx0101010011101100000000100010101001100100101100000000111001111110 -
b10101010100 /
1%
#980
0%
#985
b0 1
b10 0
bx0101111111101100000000100010101001100100101100000000111001111110 #
bx0101111111101100000000100010101001100100101100000000111001111110 -
b10101011111 /
1%
#990
0%
#995
b1 1
bx0111011111101100000000100010101001100100101100000000111001111110 #
bx0111011111101100000000100010101001100100101100000000111001111110 -
b10101110111 /
1%
#1000
0%
#1005
b10 1
bx1000010011101100000000100010101001100100101100000000111001111110 #
bx1000010011101100000000100010101001100100101100000000111001111110 -
b10110000100 /
1%
#1010
0%
#1015
b0 0
b0 1
b1 3
b1000 4
bx1010000011101100000000100010101001100100101100000000111001111110 #
bx1010000011101100000000100010101001100100101100000000111001111110 -
b10110100000 /
1%
#1020
0%
#1025
b1 1
bx101011101010000011101100000000100010101001100100101100000000111001111110 #
bx101011101010000011101100000000100010101001100100101100000000111001111110 -
b10110101110 /
1%
#1030
0%
#1035
b10 1
bx101101101010000011101100000000100010101001100100101100000000111001111110 #
bx101101101010000011101100000000100010101001100100101100000000111001111110 -
b10110110110 /
1%
#1040
0%
#1045
b0 1
b1 0
bx110010001010000011101100000000100010101001100100101100000000111001111110 #
bx110010001010000011101100000000100010101001100100101100000000111001111110 -
b10111001000 /
1%
#1050
0%
#1055
b1 1
bx110100101010000011101100000000100010101001100100101100000000111001111110 #
bx110100101010000011101100000000100010101001100100101100000000111001111110 -
b10111010010 /
1%
#1060
0%
#1065
b10 1
bx000101001010000011101100000000100010101001100100101100000000111001111110 #
bx000101001010000011101100000000100010101001100100101100000000111001111110 -
b11000010100 /
1%
#1070
0%
#1075
b0 1
b10 0
bx001000001010000011101100000000100010101001100100101100000000111001111110 #
bx001000001010000011101100000000100010101001100100101100000000111001111110 -
b11000100000 /
1%
#1080
0%
#1085
b1 1
bx001110101010000011101100000000100010101001100100101100000000111001111110 #
bx001110101010000011101100000000100010101001100100101100000000111001111110 -
b11000111010 /
1%
#1090
0%
#1095
b10 1
bx010010001010000011101100000000100010101001100100101100000000111001111110 #
bx010010001010000011101100000000100010101001100100101100000000111001111110 -
b11001001000 /
1%
#1100
0%
#1105
b0 0
b0 1
b10 3
b1001 4
bx011001101010000011101100000000100010101001100100101100000000111001111110 #
bx011001101010000011101100000000100010101001100100101100000000111001111110 -
b11001100110 /
1%
#1110
0%
#1115
b1 1
bx01110110011001101010000011101100000000100010101001100100101100000000111001111110 #
bx01110110011001101010000011101100000000100010101001100100101100000000111001111110 -
b11001110110 /
1%
#1120
0%
#1125
b10 1
bx01111111011001101010000011101100000000100010101001100100101100000000111001111110 #
bx01111111011001101010000011101100000000100010101001100100101100000000111001111110 -
b11001111111 /
1%
#1130
0%
#1135
b0 1
b1 0
bx10010011011001101010000011101100000000100010101001100100101100000000111001111110 #
bx10010011011001101010000011101100000000100010101001100100101100000000111001111110 -
b11010010011 /
1%
#1140
0%
#1145
b1 1
bx10011110011001101010000011101100000000100010101001100100101100000000111001111110 #
bx10011110011001101010000011101100000000100010101001100100101100000000111001111110 -
b11010011110 /
1%
#1150
0%
#1155
b10 1
bx11100110011001101010000011101100000000100010101001100100101100000000111001111110 #
bx11100110011001101010000011101100000000100010101001100100101100000000111001111110 -
b11011100110 /
1%
#1160
0%
#1165
b0 1
b10 0
bx11110011011001101010000011101100000000100010101001100100101100000000111001111110 #
bx11110011011001101010000011101100000000100010101001100100101100000000111001111110 -
b11011110011 /
1%
#1170
0%
#1175
b1 1
bx00001111011001101010000011101100000000100010101001100100101100000000111001111110 #
bx00001111011001101010000011101100000000100010101001100100101100000000111001111110 -
b11100001111 /
1%
#1180
0%
#1185
b10 1
bx00011110011001101010000011101100000000100010101001100100101100000000111001111110 #
bx00011110011001101010000011101100000000100010101001100100101100000000111001111110 -
b11100011110 /
1%
#1190
0%
#1195
b0 0
b0 1
b11 3
b1010 4
bx00111110011001101010000011101100000000100010101001100100101100000000111001111110 #
bx00111110011001101010000011101100000000100010101001100100101100000000111001111110 -
b11100111110 /
1%
#1200
0%
#1205
b1 1
bx0101000000111110011001101010000011101100000000100010101001100100101100000000111001111110 #
bx0101000000111110011001101010000011101100000000100010101001100100101100000000111001111110 -
b11101010000 /
1%
#1210
0%
#1215
b10 1
bx0101101000111110011001101010000011101100000000100010101001100100101100000000111001111110 #
bx0101101000111110011001101010000011101100000000100010101001100100101100000000111001111110 -
b11101011010 /
1%
#1220
0%
#1225
b0 1
b1 0
bx0111000000111110011001101010000011101100000000100010101001100100101100000000111001111110 #
bx0111000000111110011001101010000011101100000000100010101001100100101100000000111001111110 -
b11101110000 /
1%
#1230
0%
#1235
b1 1
bx0111110000111110011001101010000011101100000000100010101001100100101100000000111001111110 #
bx0111110000111110011001101010000011101100000000100010101001100100101100000000111001111110 -
b11101111100 /
1%
#1240
0%
#1245
b10 1
bx1100101000111110011001101010000011101100000000100010101001100100101100000000111001111110 #
bx1100101000111110011001101010000011101100000000100010101001100100101100000000111001111110 -
b11111001010 /
1%
#1250
0%
#1255
b0 1
b10 0
bx1101100000111110011001101010000011101100000000100010101001100100101100000000111001111110 #
bx1101100000111110011001101010000011101100000000100010101001100100101100000000111001111110 -
b11111011000 /
1%
#1260
0%
#1265
b1 1
bx1111011000111110011001101010000011101100000000100010101001100100101100000000111001111110 #
bx1111011000111110011001101010000011101100000000100010101001100100101100000000111001111110 -
b11111110110 /
1%
#1270
0%
#1275
b10 1
bx0000011000111110011001101010000011101100000000100010101001100100101100000000111001111110 #
bx0000011000111110011001101010000011101100000000100010101001100100101100000000111001111110 -
b100000000110 /
1%
#1280
0%
#1285
b0 0
b0 1
b100 3
b1011 4
bx0010100000111110011001101010000011101100000000100010101001100100101100000000111001111110 #
bx0010100000111110011001101010000011101100000000100010101001100100101100000000111001111110 -
b100000101000 /
1%
#1290
0%
#1295
b1 1
bx001111000010100000111110011001101010000011101100000000100010101001100100101100000000111001111110 #
bx001111000010100000111110011001101010000011101100000000100010101001100100101100000000111001111110 -
b100000111100 /
1%
#1300
0%
#1305
b10 1
bx010001110010100000111110011001101010000011101100000000100010101001100100101100000000111001111110 #
bx010001110010100000111110011001101010000011101100000000100010101001100100101100000000111001111110 -
b100001000111 /
1%
#1310
0%
#1315
b0 1
b1 0
bx010111110010100000111110011001101010000011101100000000100010101001100100101100000000111001111110 #
bx010111110010100000111110011001101010000011101100000000100010101001100100101100000000111001111110 -
b100001011111 /
1%
#1320
0%
#1325
b1 1
bx011011000010100000111110011001101010000011101100000000100010101001100100101100000000111001111110 #
bx011011000010100000111110011001101010000011101100000000100010101001100100101100000000111001111110 -
b100001101100 /
1%
#1330
0%
#1335
b10 1
bx110000000010100000111110011001101010000011101100000000100010101001100100101100000000111001111110 #
bx110000000010100000111110011001101010000011101100000000100010101001100100101100000000111001111110 -
b100011000000 /
1%
#1340
0%
#1345
b0 1
b10 0
bx110011110010100000111110011001101010000011101100000000100010101001100100101100000000111001111110 #
bx110011110010100000111110011001101010000011101100000000100010101001100100101100000000111001111110 -
b100011001111 /
1%
#1350
0%
#1355
b1 1
bx111011110010100000111110011001101010000011101100000000100010101001100100101100000000111001111110 #
bx111011110010100000111110011001101010000011101100000000100010101001100100101100000000111001111110 -
b100011101111 /
1%
#1360
0%
#1365
b10 1
bx000000000010100000111110011001101010000011101100000000100010101001100100101100000000111001111110 #
bx000000000010100000111110011001101010000011101100000000100010101001100100101100000000111001111110 -
b100100000000 /
1%
#1370
0%
#1375
b0 0
b0 1
b101 3
b1100 4
bx001001000010100000111110011001101010000011101100000000100010101001100100101100000000111001111110 #
bx001001000010100000111110011001101010000011101100000000100010101001100100101100000000111001111110 -
b100100100100 /
1%
#1380
0%
#1385
b1 1
bx00111010001001000010100000111110011001101010000011101100000000100010101001100100101100000000111001111110 #
bx00111010001001000010100000111110011001101010000011101100000000100010101001100100101100000000111001111110 -
b100100111010 /
1%
#1390
0%
#1395
b10 1
bx01000110001001000010100000111110011001101010000011101100000000100010101001100100101100000000111001111110 #
bx01000110001001000010100000111110011001101010000011101100000000100010101001100100101100000000111001111110 -
b100101000110 /
1%
#1400
0%
#1405
b0 1
b1 0
bx01100000001001000010100000111110011001101010000011101100000000100010101001100100101100000000111001111110 #
bx01100000001001000010100000111110011001101010000011101100000000100010101001100100101100000000111001111110 -
b100101100000 /
1%
#1410
0%
#1415
b1 1
bx01101110001001000010100000111110011001101010000011101100000000100010101001100100101100000000111001111110 #
bx01101110001001000010100000111110011001101010000011101100000000100010101001100100101100000000111001111110 -
b100101101110 /
1%
#1420
0%
#1425
b10 1
bx11001000001001000010100000111110011001101010000011101100000000100010101001100100101100000000111001111110 #
bx11001000001001000010100000111110011001101010000011101100000000100010101001100100101100000000111001111110 -
b100111001000 /
1%
#1430
0%
#1435
b0 1
b10 0
bx11011000001001000010100000111110011001101010000011101100000000100010101001100100101100000000111001111110 #
bx11011000001001000010100000111110011001101010000011101100000000100010101001100100101100000000111001111110 -
b100111011000 /
1%
#1440
0%
#1445
b1 1
bx11111010001001000010100000111110011001101010000011101100000000100010101001100100101100000000111001111110 #
bx11111010001001000010100000111110011001101010000011101100000000100010101001100100101100000000111001111110 -
b100111111010 /
1%
#1450
0%
#1455
b10 1
bx00001100001001000010100000111110011001101010000011101100000000100010101001100100101100000000111001111110 #
bx00001100001001000010100000111110011001101010000011101100000000100010101001100100101100000000111001111110 -
b101000001100 /
1%
#1460
0%
#1465
b0 0
b0 1
b110 3
b1101 4
bx00110010001001000010100000111110011001101010000011101100000000100010101001100100101100000000111001111110 #
bx00110010001001000010100000111110011001101010000011101100000000100010101001100100101100000000111001111110 -
b101000110010 /
1%
#1470
0%
#1475
b1 1
bx0100101000110010001001000010100000111110011001101010000011101100000000100010101001100100101100000000111001111110 #
bx0100101000110010001001000010100000111110011001101010000011101100000000100010101001100100101100000000111001111110 -
b101001001010 /
1%
#1480
0%
#1485
b10 1
bx0101011100110010001001000010100000111110011001101010000011101100000000100010101001100100101100000000111001111110 #
bx0101011100110010001001000010100000111110011001101010000011101100000000100010101001100100101100000000111001111110 -
b101001010111 /
1%
#1490
0%
#1495
b0 1
b1 0
bx0111001100110010001001000010100000111110011001101010000011101100000000100010101001100100101100000000111001111110 #
bx0111001100110010001001000010100000111110011001101010000011101100000000100010101001100100101100000000111001111110 -
b101001110011 /
1%
#1500
0%
#1505
b1 1
bx1000001000110010001001000010100000111110011001101010000011101100000000100010101001100100101100000000111001111110 #
bx1000001000110010001001000010100000111110011001101010000011101100000000100010101001100100101100000000111001111110 -
b101010000010 /
1%
#1510
0%
#1515
b10 1
bx1110001000110010001001000010100000111110011001101010000011101100000000100010101001100100101100000000111001111110 #
bx1110001000110010001001000010100000111110011001101010000011101100000000100010101001100100101100000000111001111110 -
b101011100010 /
1%
#1520
0%
#1525
b0 1
b10 0
bx1111001100110010001001000010100000111110011001101010000011101100000000100010101001100100101100000000111001111110 #
bx1111001100110010001001000010100000111110011001101010000011101100000000100010101001100100101100000000111001111110 -
b101011110011 /
1%
#1530
0%
#1535
b1 1
bx0001011100110010001001000010100000111110011001101010000011101100000000100010101001100100101100000000111001111110 #
bx0001011100110010001001000010100000111110011001101010000011101100000000100010101001100100101100000000111001111110 -
b101100010111 /
1%
#1540
0%
#1545
b10 1
bx0010101000110010001001000010100000111110011001101010000011101100000000100010101001100100101100000000111001111110 #
bx0010101000110010001001000010100000111110011001101010000011101100000000100010101001100100101100000000111001111110 -
b101100101010 /
1%
#1550
0%
#1555
b0 3
b0 0
b0 1
b10 2
b1110 4
bx0101001000110010001001000010100000111110011001101010000011101100000000100010101001100100101100000000111001111110 #
bx0101001000110010001001000010100000111110011001101010000011101100000000100010101001100100101100000000111001111110 -
b101101010010 /
1%
#1560
0%
#1565
b1 1
bx011001000101001000110010001001000010100000111110011001101010000011101100000000100010101001100100101100000000111001111110 #
bx011001000101001000110010001001000010100000111110011001101010000011101100000000100010101001100100101100000000111001111110 -
b101101100100 /
1%
#1570
0%
#1575
b10 1
bx011011100101001000110010001001000010100000111110011001101010000011101100000000100010101001100100101100000000111001111110 #
bx011011100101001000110010001001000010100000111110011001101010000011101100000000100010101001100100101100000000111001111110 -
b101101101110 /
1%
#1580
0%
#1585
b0 1
b1 0
bx100001000101001000110010001001000010100000111110011001101010000011101100000000100010101001100100101100000000111001111110 #
bx100001000101001000110010001001000010100000111110011001101010000011101100000000100010101001100100101100000000111001111110 -
b101110000100 /
1%
#1590
0%
#1595
b1 1
bx100100000101001000110010001001000010100000111110011001101010000011101100000000100010101001100100101100000000111001111110 #
bx100100000101001000110010001001000010100000111110011001101010000011101100000000100010101001100100101100000000111001111110 -
b101110010000 /
1%
#1600
0%
#1605
b10 1
bx110111100101001000110010001001000010100000111110011001101010000011101100000000100010101001100100101100000000111001111110 #
bx110111100101001000110010001001000010100000111110011001101010000011101100000000100010101001100100101100000000111001111110 -
b101111011110 /
1%
#1610
0%
#1615
b0 1
b10 0
bx111011000101001000110010001001000010100000111110011001101010000011101100000000100010101001100100101100000000111001111110 #
bx111011000101001000110010001001000010100000111110011001101010000011101100000000100010101001100100101100000000111001111110 -
b101111101100 /
1%
#1620
0%
#1625
b1 1
bx000010100101001000110010001001000010100000111110011001101010000011101100000000100010101001100100101100000000111001111110 #
bx000010100101001000110010001001000010100000111110011001101010000011101100000000100010101001100100101100000000111001111110 -
b110000001010 /
1%
#1630
0%
#1635
b10 1
bx000110100101001000110010001001000010100000111110011001101010000011101100000000100010101001100100101100000000111001111110 #
bx000110100101001000110010001001000010100000111110011001101010000011101100000000100010101001100100101100000000111001111110 -
b110000011010 /
1%
#1640
0%
#1645
b0 0
b0 1
b1 3
b1111 4
bx001111000101001000110010001001000010100000111110011001101010000011101100000000100010101001100100101100000000111001111110 #
bx001111000101001000110010001001000010100000111110011001101010000011101100000000100010101001100100101100000000111001111110 -
b110000111100 /
1%
#1650
0%
#1655
b1 1
bx01010000001111000101001000110010001001000010100000111110011001101010000011101100000000100010101001100100101100000000111001111110 #
bx01010000001111000101001000110010001001000010100000111110011001101010000011101100000000100010101001100100101100000000111001111110 -
b110001010000 /
1%
#1660
0%
#1665
b10 1
bx01011011001111000101001000110010001001000010100000111110011001101010000011101100000000100010101001100100101100000000111001111110 #
bx01011011001111000101001000110010001001000010100000111110011001101010000011101100000000100010101001100100101100000000111001111110 -
b110001011011 /
1%
#1670
0%
